<?xml version="1.0" encoding="UTF-8"?>
<bibl xmlns="http://www.tei-c.org/ns/1.0"
      xml:id="b59188"
      type="article"
      subtype="book"
      xml:lang="en">
   <title level="a" type="main">Hidden Verses.</title>
   <series>
      <title level="s" type="main">BICS Supplement.</title>
      <biblScope type="volume">51</biblScope>
   </series>
   <author n="1">
      <forename>Eric Walter</forename>
      <surname>Handley</surname>
   </author>
   <biblScope type="pp" from="166" to="174">166-174</biblScope>
   <note resp="#BP">Voir pp. 172-173: Bacchylide, Épinicies 3, 19-22 et 37-40; - 170: les Sicyoniens de Ménandre et Euripide, Oreste; - 173: écho d'Aristophane, Grenouilles, dans le Dyscolos.</note>
   <relatedItem type="appearsIn">
      <bibl>
         <ptr target="http://papyri.info/biblio/11485"/>
         <!--ignore - start, i.e. SoSOL users may not edit this-->
         <title level="m" type="main">Vir bonus discendi peritus. Studies in Celebration of Otto Skutsch's Eightieth Birthday</title>
         <editor/>
         <date>1988</date>
         <!--ignore - stop-->
      </bibl>
   </relatedItem>
   <idno type="pi">59188</idno>
   <idno type="bp">1988-0297</idno>
   <seg type="original" subtype="index" resp="#BP">364 Bacchylides Menander B</seg>
   <seg type="original" subtype="titre" resp="#BP">Handley Eric Walter, Hidden Verses.</seg>
   <seg type="original" subtype="publication" resp="#BP">Nicholas Horsfall (Ed.), Vir bonus discendi peritus. Studies in Celebration of Otto Skutsch's Eightieth Birthday = BICS Supplement. 51 (London, 1988) pp. 166-174.</seg>
   <seg type="original" subtype="resume" resp="#BP">Voir pp. 172-173: Bacchylide, Épinicies 3, 19-22 et 37-40; - 170: les Sicyoniens de Ménandre et Euripide, Oreste; - 173: écho d'Aristophane, Grenouilles, dans le Dyscolos.</seg>
   <seg type="original" subtype="nom" resp="#BP">Handley</seg>
</bibl>
