<?xml version="1.0" encoding="UTF-8"?>
<bibl xmlns="http://www.tei-c.org/ns/1.0"
      xml:id="b67843"
      type="article"
      subtype="journal">
   <title level="a" type="main">Callimachus fr. 1.9-12 Again.</title>
   <author n="1">
      <forename>Konstantinos</forename>
      <surname>Spanoudakis</surname>
   </author>
   <date>1998</date>
   <biblScope type="pp" from="59" to="61">59-61</biblScope>
   <note resp="#BP">À propos de: Guido BASTIANINI, Κατὰ λεπτόν in Callimaco (Fr. 1.11 Pfeiffer), Ὁδοὶ διζήσιος. Le vie della ricerca. Studi in onore di Francesco Adorno (Firenze, 1996) pp. 69-80, 3 figg.; - Wolfgang LUPPE, Kallimachos, Aitien-Prolog V. 7-12, ZPE 115 (1997) pp. 50-54, 1 fig.</note>
   <ptr target="http://www.jstor.org/stable/20190188"/>
   <relatedItem type="appearsIn">
      <bibl>
         <ptr target="http://papyri.info/biblio/511"/>
         <!--ignore - start, i.e. SoSOL users may not edit this-->
         <title level="j" type="short-BP">ZPE</title>
         <!--ignore - stop-->
      </bibl>
   </relatedItem>
   <biblScope type="issue">121</biblScope>
   <idno type="pi">67843</idno>
   <idno type="bp">1998-0607</idno>
   <idno type="bp_old">98/3/245</idno>
   <seg type="original" subtype="index" resp="#BP">364 Callimachus</seg>
   <seg type="original" subtype="titre" resp="#BP">SPANOUDAKIS Konstantinos, Callimachus fr. 1.9-12 Again.</seg>
   <seg type="original" subtype="publication" resp="#BP">ZPE 121 (1998) pp. 59-61.</seg>
   <seg type="original" subtype="resume" resp="#BP">À propos de: Guido BASTIANINI, Κατὰ λεπτόν in Callimaco (Fr. 1.11 Pfeiffer), Ὁδοὶ διζήσιος. Le vie della ricerca. Studi in onore di Francesco Adorno (Firenze, 1996) pp. 69-80, 3 figg.; - Wolfgang LUPPE, Kallimachos, Aitien-Prolog V. 7-12, ZPE 115 (1997) pp. 50-54, 1 fig.</seg>
   <seg type="original" subtype="nom" resp="#BP">Spanoudakis</seg>
</bibl>
