<?xml version="1.0" encoding="UTF-8"?>
<bibl xmlns="http://www.tei-c.org/ns/1.0"
      xml:id="b63041"
      type="article"
      subtype="journal">
   <title level="a" type="main">Tre note ai frammenti di Pindaro.</title>
   <author n="1">
      <forename>Franco</forename>
      <surname>Ferrari</surname>
   </author>
   <date>1993</date>
   <biblScope type="pp" from="47" to="54">47-54</biblScope>
   <note resp="#BP">I. Un titolo: l'adscriptum del fr. 140b Maehler. - II. Sul fr. 334 (a) Maehler. - III. Sul fr. 346 (a) 1-2 e (b) 1-3 Maehler.</note>
   <relatedItem type="appearsIn">
      <bibl>
         <ptr target="http://papyri.info/biblio/464"/>
         <!--ignore - start, i.e. SoSOL users may not edit this-->
         <title level="j" type="short-BP">StIt</title>
         <!--ignore - stop-->
      </bibl>
   </relatedItem>
   <biblScope type="issue">86 = 3a s., 11</biblScope>
   <idno type="pi">63041</idno>
   <idno type="bp">1993-0230</idno>
   <idno type="bp_old">95/3/115</idno>
   <seg type="original" subtype="index" resp="#BP">364 Pindarus</seg>
   <seg type="original" subtype="titre" resp="#BP">FERRARI Franco, Tre note ai frammenti di Pindaro.</seg>
   <seg type="original" subtype="publication" resp="#BP">StIt 86 = 3a s., 11 (1993) pp. 47-54.</seg>
   <seg type="original" subtype="resume" resp="#BP">I. Un titolo: l'adscriptum del fr. 140b Maehler. - II. Sul fr. 334 (a) Maehler. - III. Sul fr. 346 (a) 1-2 e (b) 1-3 Maehler.</seg>
   <seg type="original" subtype="nom" resp="#BP">Ferrari</seg>
</bibl>
