<?xml version="1.0" encoding="UTF-8"?>
<bibl xmlns="http://www.tei-c.org/ns/1.0" xml:id="b7404" type="book">
   <title level="m" type="main">The Roman Imperial Army of the First and Second Centuries A.D.</title>
   <author n="1">
      <forename>Graham</forename>
      <surname>Webster</surname>
   </author>
   <date>1969</date>
   <pubPlace>London</pubPlace>
   <publisher>Adam and Charles Black</publisher>
   <note type="pageCount">330</note>
   <note type="illustration">52 figg. et 31 pll.</note>
   <note resp="#BP">Utilisation occasionnelle des papyrus.</note>
   <idno type="pi">7404</idno>
   <idno type="bp">1969-0409</idno>
   <seg type="original" subtype="index" resp="#BP">620</seg>
   <seg type="original" subtype="titre" resp="#BP">Webster Graham, The Roman Imperial Army of the First and Second Centuries A.D.</seg>
   <seg type="original" subtype="publication" resp="#BP">London, Adam and Charles Black, 1969, 8°, 330 pp., 52 figg. et 31 pll.</seg>
   <seg type="original" subtype="resume" resp="#BP">Utilisation occasionnelle des papyrus.</seg>
   <seg type="original" subtype="cr" resp="#BP">C.R. par James Frank Gilliam, Gnomon 47 (1975) pp. 310-313.</seg>
   <seg type="original" subtype="nom" resp="#BP">Webster</seg>
</bibl>
