<?xml version='1.0' encoding='UTF-8'?>
<bibl xmlns="http://www.tei-c.org/ns/1.0" xml:id="b95058" type="book">
  <title level="m" type="main">Arabische Briefe des 7. bis 13. Jahrhundert aus den Staatlichen Museen Berlin</title>
  <note type="papyrological-series">
    <bibl>
      <title level="s" type="short-Checklist" n="1">CPR 16</title>
    </bibl>
  </note>
  <note type="subject">Papyri</note>
  <author n="1">
    <forename>Werner</forename>
    <surname>Diem</surname>
  </author>
  <date>1993</date>
  <pubPlace n="1">Vienna</pubPlace>
  <publisher n="1">Harrasowitz</publisher>
  <idno type="isbn">9783851192520</idno>
  <idno type="checklist">clz-I65WWB2U</idno>
  <idno type="pi">95058</idno>
</bibl>