<?xml version="1.0" encoding="UTF-8"?>
<bibl xmlns="http://www.tei-c.org/ns/1.0" xml:id="b18203" type="book">
   <title level="m" type="main">Legitimacy and Law in the Roman World. Tabulae in Roman Belief and Practice.</title>
   <author n="1">
      <forename>Elizabeth A.</forename>
      <surname>Meyer</surname>
   </author>
   <date>2004</date>
   <pubPlace>Cambridge</pubPlace>
   <publisher>Cambridge University Press</publisher>
   <note type="pageCount">353</note>
   <note type="prefacePageCount">xvi</note>
   <note type="illustration">9 figg.</note>
   <note resp="#BP">See in part. pp. 169-215: Chapter 7. Roman tablets and related forms in the Roman provinces (30 BC-AD 260). Uses the papyrological evidence.</note>
   <idno type="pi">18203</idno>
   <idno type="bp">2004-0660</idno>
   <idno type="bp_old">04/3/211</idno>
   <idno type="isbn">0-521-49701-9</idno>
   <seg type="original" subtype="index" resp="#BP">600 650</seg>
   <seg type="original" subtype="titre" resp="#BP">MEYER Elizabeth A., Legitimacy and Law in the Roman World. Tabulae in Roman Belief and Practice.</seg>
   <seg type="original" subtype="publication" resp="#BP">Cambridge, Cambridge University Press, 2004, 8°, xvi-353 pp., 9 figg. ISBN 0-521-49701-9. £50.</seg>
   <seg type="original" subtype="resume" resp="#BP">See in part. pp. 169-215: Chapter 7. Roman tablets and related forms in the Roman provinces (30 BC-AD 260). Uses the papyrological evidence.</seg>
   <seg type="original" subtype="nom" resp="#BP">Meyer</seg>
</bibl>
