<bibl xml:id="b18955" type="book">
  <title level="m" type="main">Sophrone de Jérusalem: Miracles des saints Cyr et Jean (BHG I 477-479). (Collections de l'Université Marc-Bloch - Strasbourg. Études d'Archéologie et d'Histoire ancienne.)</title>
  <author n="1">
    <surname>GASCOU</surname>
    <forename>Jean</forename>
  </author>
  <pubPlace>Paris</pubPlace>
  <publisher>De Boccard</publisher>
  <date>2006</date>
  <note type="pageCount">242</note>
  <note resp="#BP">Fait suite à: IDEM, Les origines du culte des saints Cyr et Jean (HAL-SHS, 2006) [uniquement accessible en ligne, en téléchargement gratuit: &lt; http://halshs.archives-ouvertes.fr/halshs-00009140 &gt;]. - I. Introduction. - II. Traduction commentée. - III. Index.</note>
  <idno type="bp">06/0271</idno>
  <idno type="bp_old">07/1/098</idno>
  <idno type="isbn">2-7018-0209-1</idno>
  <note type="titre" resp="#BPLegacy">GASCOU Jean (traduction commentée par), Sophrone de Jérusalem: Miracles des saints Cyr et Jean (BHG I 477-479). (Collections de l'Université Marc-Bloch - Strasbourg. Études d'Archéologie et d'Histoire ancienne.)</note>
  <note type="publication" resp="#BPLegacy">Paris, De Boccard, 2006, 8°, 242 pp. ISBN 2-7018-0209-1. €20.</note>
  <note type="index" resp="#BPLegacy">364 Sophronius Damascenus sive Hierosolymitanus</note>
  <note type="nom" resp="#BPLegacy">Gascou</note>
</bibl>