<bibl xml:id="b60156" type="article" subtype="book" xml:lang="en">
  <title level="a" type="main">Theben-West und Theben-Ost (31 demotische r-rh=w Ostraka aus dem British Museum).</title>
  <author n="1">
    <surname>KAPLONY-HECKEL</surname>
    <forename>Ursula</forename>
  </author>
  <relatedItem type="appearsIn">
    <bibl>
      <ptr target="bibl:12176"/>
      <!--ignore - start, i.e. SoSOL users may not edit this-->
      <title level="m" type="main">Studies in Egyptology Presented to Miriam Lichtheim</title>
      <author>KAPLONY-HECKEL, Ursula</author>
      <editor>ISRAELIT-GROLL, Sarah</editor>
      <date>1990</date>
      <!--ignore - stop-->
    </bibl>
  </relatedItem>
  <biblScope type="pp" from="517" to="624"/>
  <note resp="#BP">Siehe S. 606-607, Nr. 27: 6 Zeilen Demotisch, 2 Zeilen Griechisch (Entzifferung: Bärbel KRAMER). 98/97 oder 65/64 v.Chr.</note>
  <idno type="bp">90/0835</idno>
  <note type="titre" resp="#BPLegacy">KAPLONY-HECKEL Ursula, Theben-West und Theben-Ost (31 demotische r-rh=w Ostraka aus dem British Museum).</note>
  <note type="publication" resp="#BPLegacy">Sarah ISRAELIT-GROLL (Ed.), Studies in Egyptology Presented to Miriam Lichtheim (Jerusalem, 1990) II, pp. 517-624, tabl., fac-sim.</note>
  <note type="index" resp="#BPLegacy">142.12 / 142.4</note>
  <note type="indexBis" resp="#BPLegacy">142.12 / 142.4 O. Lond. dem. Inv. 25796</note>
  <note type="nom" resp="#BPLegacy">Kaplony-Heckel Kramer</note>
</bibl>