<?xml version="1.0" encoding="UTF-8"?>
<bibl xmlns="http://www.tei-c.org/ns/1.0"
      xml:id="b58987"
      type="article"
      subtype="journal">
   <title level="a" type="main">Un frammento del libro XI di Tito Livio?</title>
   <author n="1">
      <forename>Benedetto</forename>
      <surname>Bravo</surname>
   </author>
   <author n="2">
      <forename>Miriam</forename>
      <surname>Griffin</surname>
   </author>
   <date>1988</date>
   <biblScope type="pp" from="477" to="521">477-521</biblScope>
   <note resp="#BP">Fouilles polonaises de Naqlun, 1986. Fragment de parchemin conservant les restes de deux colonnes d'écriture sur chaque côté, Ve s. p.C. Édition et étude philologique par B.Br. (en italien). Étude historique par M.Gr. (en anglais).</note>
   <relatedItem type="appearsIn">
      <bibl>
         <ptr target="http://papyri.info/biblio/1039"/>
         <!--ignore - start, i.e. SoSOL users may not edit this-->
         <title level="j" type="short-BP">Athenaeum</title>
         <!--ignore - stop-->
      </bibl>
   </relatedItem>
   <biblScope type="issue">66</biblScope>
   <relatedItem type="mentions" n="1">
      <bibl>
         <idno type="invNo">P. Naqlun Inv. 15-86</idno>
      </bibl>
   </relatedItem>
   <idno type="pi">58987</idno>
   <idno type="bp">1988-0096</idno>
   <seg type="original" subtype="index" resp="#BP">141.5 365 Livius (Titus)</seg>
   <seg type="original" subtype="indexBis" resp="#BP">141.5 P. Naqlun Inv. 15-86</seg>
   <seg type="original" subtype="titre" resp="#BP">Bravo Benedetto e Miriam Griffin, Un frammento del libro XI di Tito Livio?</seg>
   <seg type="original" subtype="publication" resp="#BP">Athenaeum 66 (1988) pp. 477-521 et 8 pll.</seg>
   <seg type="original" subtype="resume" resp="#BP">Fouilles polonaises de Naqlun, 1986. Fragment de parchemin conservant les restes de deux colonnes d'écriture sur chaque côté, Ve s. p.C. Édition et étude philologique par B.Br. (en italien). Étude historique par M.Gr. (en anglais).</seg>
   <seg type="original" subtype="nom" resp="#BP">Bravo Griffin</seg>
</bibl>
