<?xml version="1.0" encoding="UTF-8"?>
<bibl xmlns="http://www.tei-c.org/ns/1.0"
      xml:id="b35434"
      type="article"
      subtype="journal">
   <title level="a" type="main">Zur Diogenes-Tradition.</title>
   <author n="1">
      <forename>Gunnar</forename>
      <surname>Rudberg</surname>
   </author>
   <date>1935</date>
   <biblScope type="pp" from="22" to="43">22-43</biblScope>
   <relatedItem type="appearsIn">
      <bibl>
         <ptr target="http://papyri.info/biblio/470"/>
         <!--ignore - start, i.e. SoSOL users may not edit this-->
         <title level="j" type="short-BP">SymbOslo</title>
         <!--ignore - stop-->
      </bibl>
   </relatedItem>
   <biblScope type="issue">14</biblScope>
   <idno type="pi">35434</idno>
   <idno type="bp">1935-0309</idno>
   <seg type="original" subtype="index" resp="#BP">364 Diogenes Cynicus</seg>
   <seg type="original" subtype="titre" resp="#BP">Rudberg Gunnar, Zur Diogenes-Tradition.</seg>
   <seg type="original" subtype="publication" resp="#BP">SymbOslo 14 (1935) pp. 22-43.</seg>
   <seg type="original" subtype="nom" resp="#BP">Rudberg</seg>
</bibl>
