<bibl xml:id="b52429" type="article" subtype="book" xml:lang="en">
  <title level="a" type="main">Sarapis debout: un problème iconographique.</title>
  <author n="1">
    <surname>Tran Tam Tinh</surname>
    <forename>Vincent</forename>
  </author>
  <relatedItem type="appearsIn">
    <bibl>
      <ptr target="bibl:9222"/>
      <!--ignore - start, i.e. SoSOL users may not edit this-->
      <title level="m" type="main">First International Congress of Egyptology</title>
      <author>Tran Tam Tinh, Vincent</author>
      <editor>Walter F. Reineke</editor>
      <date>1979</date>
      <!--ignore - stop-->
    </bibl>
  </relatedItem>
  <biblScope type="pp" from="645" to="649"/>
  <idno type="bp">79/0520</idno>
  <note type="titre" resp="#BPLegacy">Tran Tam Tinh Vincent, Sarapis debout: un problème iconographique.</note>
  <note type="publication" resp="#BPLegacy">Walter F. Reineke (Ed.), First International Congress of Egyptology (Berlin, 1979) pp. 645-649 et pll. 87-89.</note>
  <note type="index" resp="#BPLegacy">712</note>
  <note type="nom" resp="#BPLegacy">Tran Tam Tinh</note>
</bibl>