<bibl xml:id="b38871" type="article" subtype="journal">
  <title level="a" type="main">À propos de deux graffiti grecs d'une tombe siwite.</title>
  <author n="1">
    <surname>Rémondon</surname>
    <forename>Roger</forename>
  </author>
  <relatedItem type="appearsIn">
    <bibl>
      <ptr target="bibl:174"/>
      <!--ignore - start, i.e. SoSOL users may not edit this-->
      <title level="j" type="short">ChrEg</title>
      <!--ignore - stop-->
    </bibl>
  </relatedItem>
  <biblScope type="issue">26</biblScope>
  <date>1951</date>
  <biblScope type="pp" from="156" to="161"/>
  <note resp="#BP">Nécropole de Gebel el-Mota, Ier siècle a.C. et Ier siècle p.C. - Observations sur les stolistes et les nécrostolistes.</note>
  <idno type="bp">51/0250</idno>
  <note type="titre" resp="#BPLegacy">Rémondon Roger, À propos de deux graffiti grecs d'une tombe siwite.</note>
  <note type="publication" resp="#BPLegacy">ChrEg 26 (1951) No. 51, pp. 156-161.</note>
  <note type="index" resp="#BPLegacy">413 756 910</note>
  <note type="nom" resp="#BPLegacy">Rémondon</note>
</bibl>