<?xml version="1.0" encoding="UTF-8"?>
<bibl xmlns="http://www.tei-c.org/ns/1.0"
      xml:id="b38970"
      type="article"
      subtype="journal">
   <title level="a" type="main">[Traduction poétique des Epitrepontes en hongrois.]</title>
   <author n="1">
      <forename>Gábor</forename>
      <surname>Devecseri</surname>
   </author>
   <date>1949</date>
   <biblScope type="pp" from="172" to="182">172-182</biblScope>
   <relatedItem type="appearsIn">
      <bibl>
         <ptr target="http://papyri.info/biblio/1512"/>
         <!--ignore - start, i.e. SoSOL users may not edit this-->
         <title level="j" type="short-BP">Magyarok</title>
         <!--ignore - stop-->
      </bibl>
   </relatedItem>
   <biblScope type="issue">5</biblScope>
   <idno type="pi">38970</idno>
   <idno type="bp">1949-0080</idno>
   <seg type="original" subtype="index" resp="#BP">364 Menander C Epitrepontes</seg>
   <seg type="original" subtype="titre" resp="#BP">Devecseri Gábor, [Traduction poétique des Epitrepontes en hongrois.]</seg>
   <seg type="original" subtype="publication" resp="#BP">Magyarok 5 (1949) pp. 172-182.</seg>
   <seg type="original" subtype="nom" resp="#BP">Devecseri</seg>
</bibl>
