<bibl xml:id="b44028" type="article" subtype="book" xml:lang="de">
  <title level="a" type="main">Die 채lteste Darstellung des Gekreuzigten auf einer magischen Gemme des 3. (?) Jahrhunderts.</title>
  <author n="1">
    <surname>Derchain</surname>
    <forename>Philippe</forename>
  </author>
  <relatedItem type="appearsIn">
    <bibl>
      <ptr target="bibl:6527"/>
      <!--ignore - start, i.e. SoSOL users may not edit this-->
      <title level="m" type="main">Christentum am Nil. Internationale Arbeitstagung zur Ausstellung 'Koptische Kunst'. Essen, Villa H체gel, 23.-25. Juli 1963</title>
      <author>Derchain, Philippe</author>
      <editor>Klaus Wessel</editor>
      <date>1964</date>
      <!--ignore - stop-->
    </bibl>
  </relatedItem>
  <biblScope type="pp" from="108" to="113"/>
  <note resp="#BP">Paris, Collection Roger Pereire.</note>
  <idno type="bp">64/0115</idno>
  <note type="titre" resp="#BPLegacy">Derchain Philippe, Die 채lteste Darstellung des Gekreuzigten auf einer magischen Gemme des 3. (?) Jahrhunderts.</note>
  <note type="publication" resp="#BPLegacy">Klaus Wessel (Hg.), Christentum am Nil. Internationale Arbeitstagung zur Ausstellung 'Koptische Kunst'. Essen, Villa H체gel, 23.-25. Juli 1963 (Recklinghausen, 1964) pp. 108-113, figg. 55-56.</note>
  <note type="index" resp="#BPLegacy">713 880</note>
  <note type="nom" resp="#BPLegacy">Derchain</note>
</bibl>