<bibl xml:id="b44277" type="article" subtype="journal">
  <title level="a" type="main">Einige Bemerkungen über einen Katalog mit Werken klassischer Schriftsteller.</title>
  <author n="1">
    <surname>Sijpesteijn</surname>
    <forename>P.J.</forename>
  </author>
  <relatedItem type="appearsIn">
    <bibl>
      <ptr target="bibl:912"/>
      <!--ignore - start, i.e. SoSOL users may not edit this-->
      <title level="j" type="short">Aegyptus</title>
      <!--ignore - stop-->
    </bibl>
  </relatedItem>
  <biblScope type="issue">44</biblScope>
  <date>1964</date>
  <biblScope type="pp" from="20" to="25"/>
  <note resp="#BP">P.S.I. Inv. 19662 (= Pack2 2087).</note>
  <idno type="bp">64/0364</idno>
  <note type="titre" resp="#BPLegacy">Sijpesteijn P.J., Einige Bemerkungen über einen Katalog mit Werken klassischer Schriftsteller.</note>
  <note type="publication" resp="#BPLegacy">Aegyptus 44 (1964) pp. 20-25.</note>
  <note type="index" resp="#BPLegacy">364 Catalogi Librorum</note>
  <note type="nom" resp="#BPLegacy">Sijpesteijn</note>
</bibl>