<bibl xmlns="http://www.tei-c.org/ns/1.0" xml:id="b27689" type="review">
  <author>M. J. Costelloe</author>
  <date>1977</date>
  <biblScope type="pp">pp. 125-126</biblScope>
  <biblScope type="issue">16</biblScope>
  <relatedItem type="appearsIn">
    <bibl>
      <ptr target="bibl:466"/>
      <!--ignore - start, i.e. SoSOL users may not edit this-->
      <title level="j" type="short">StPap</title>
      <!--ignore - stop-->
    </bibl>
  </relatedItem>
  <relatedItem type="reviews" n="1">
    <bibl>
      <ptr target="bibl:8470"/>
      <!--ignore - start, i.e. SoSOL users may not edit this-->
      <title level="m" type="main">[Michigan Papyri. Volume XII.] Michigan Papyri. (American Studies in Papyrology. 14.)</title>
      <author>Browne, Gerald M.</author>
      <!--ignore - stop-->
    </bibl>
  </relatedItem>
  <seg type="original" subtype="cr" resp="#BP">M. J. Costelloe, StPap 16 (1977) pp. 125-126.</seg>
</bibl>