<bibl xml:id="b65625" type="article" subtype="journal">
  <title level="a" type="main">The Excavations at Ismant el-Kharab 1995/6 and 1996/7: A Brief Report.</title>
  <author n="1">
    <surname>HOPE</surname>
    <forename>Colin A.</forename>
  </author>
  <author n="2">
    <forename>Gillian E.</forename>
    <surname>BOWEN</surname>
  </author>
  <relatedItem type="appearsIn">
    <bibl>
      <ptr target="bibl:103"/>
      <!--ignore - start, i.e. SoSOL users may not edit this-->
      <title level="j" type="short">BACE</title>
      <!--ignore - stop-->
    </bibl>
  </relatedItem>
  <biblScope type="issue">8</biblScope>
  <date>1997</date>
  <biblScope type="pp" from="49" to="64"/>
  <note resp="#BP">The excavations were conducted in 4 parts of the site: the East Church, the colonnaded hall, the residential quarter, the Main Temple of Tutu (papyrus' finds, ostraka, wooden boards, coins).</note>
  <idno type="bp">97/0341</idno>
  <idno type="bp_old">97/4/070</idno>
  <note type="titre" resp="#BPLegacy">HOPE Colin A. and Gillian E. BOWEN, The Excavations at Ismant el-Kharab 1995/6 and 1996/7: A Brief Report.</note>
  <note type="publication" resp="#BPLegacy">BACE 8 (1997) pp. 49-64 et pll. 4-9.</note>
  <note type="index" resp="#BPLegacy">241 Kellis 810</note>
  <note type="nom" resp="#BPLegacy">Hope Bowen</note>
</bibl>