<?xml version="1.0" encoding="UTF-8"?>
<bibl xmlns="http://www.tei-c.org/ns/1.0"
      xml:id="b51283"
      type="article"
      subtype="journal">
   <title level="a" type="main">Le substantif "chenas" et le nom d'homme "Chenas".</title>
   <author n="1">
      <forename>Willy</forename>
      <surname>Clarysse</surname>
   </author>
   <author n="2">
      <forename>Olivier</forename>
      <surname>Masson</surname>
   </author>
   <date>1976</date>
   <biblScope type="pp" from="231" to="231">231</biblScope>
   <relatedItem type="appearsIn">
      <bibl>
         <ptr target="http://papyri.info/biblio/511"/>
         <!--ignore - start, i.e. SoSOL users may not edit this-->
         <title level="j" type="short-BP">ZPE</title>
         <!--ignore - stop-->
      </bibl>
   </relatedItem>
   <biblScope type="issue">20</biblScope>
   <relatedItem type="mentions" n="1">
      <bibl>
         <title level="s" type="short">S.B.</title>
         <biblScope type="vol">I</biblScope>
         <biblScope type="num">5377</biblScope>
         <idno type="ddb">sb;1;5377</idno>
      </bibl>
   </relatedItem>
   <idno type="pi">51283</idno>
   <idno type="bp">1976-0111</idno>
   <seg type="original" subtype="index" resp="#BP">145.4 413 416</seg>
   <seg type="original" subtype="indexBis" resp="#BP">145.4 S.B. I, 5377</seg>
   <seg type="original" subtype="titre" resp="#BP">Clarysse Willy et Olivier Masson, Le substantif "chenas" et le nom d'homme "Chenas".</seg>
   <seg type="original" subtype="publication" resp="#BP">ZPE 20 (1976) p. 231.</seg>
   <seg type="original" subtype="nom" resp="#BP">Clarysse Masson</seg>
</bibl>
