<?xml version="1.0" encoding="UTF-8"?>
<bibl xmlns="http://www.tei-c.org/ns/1.0"
      xml:id="b70449"
      type="article"
      subtype="journal">
   <title level="a" type="main">Antifonte: filosofía y literatura. Avec résumé en anglais.</title>
   <author n="1">
      <forename>Gerardo</forename>
      <surname>Ramírez Vidal</surname>
   </author>
   <date>2001</date>
   <biblScope type="pp" from="33" to="53">33-53</biblScope>
   <note resp="#BP">Non vidimus. Cf. APh 72 (2003) No. 242.</note>
   <relatedItem type="appearsIn">
      <bibl>
         <ptr target="http://papyri.info/biblio/1610"/>
         <!--ignore - start, i.e. SoSOL users may not edit this-->
         <title level="j" type="short-BP">Nova Tellus</title>
         <!--ignore - stop-->
      </bibl>
   </relatedItem>
   <biblScope type="issue">19</biblScope>
   <idno type="pi">70449</idno>
   <idno type="bp">2001-0725</idno>
   <idno type="bp_old">03/4/206</idno>
   <seg type="original" subtype="index" resp="#BP">364 Antiphon Orator vel Sophistes</seg>
   <seg type="original" subtype="titre" resp="#BP">RAMÍREZ VIDAL Gerardo, Antifonte: filosofía y literatura. Avec résumé en anglais.</seg>
   <seg type="original" subtype="publication" resp="#BP">Nova Tellus 19 (2001) No. 2, pp. 33-53.</seg>
   <seg type="original" subtype="resume" resp="#BP">Non vidimus. Cf. APh 72 (2003) No. 242.</seg>
   <seg type="original" subtype="nom" resp="#BP">Ramírez</seg>
</bibl>
