<?xml version="1.0" encoding="UTF-8"?>
<bibl xmlns="http://www.tei-c.org/ns/1.0" xml:id="b82972" type="review">
  <author>
      <forename>Georg A.</forename>
      <surname>Plattner</surname>
   </author>
   <date>2009</date>
  <biblScope type="pp" from="111" to="113">111-113</biblScope>
  <relatedItem type="appearsIn">
      <bibl>
         <ptr target="http://papyri.info/biblio/378"/>
         <!--ignore - start, i.e. SoSOL users may not edit this-->
         <title level="j" type="short">RA</title>
         <!--ignore - stop-->
      </bibl>
  </relatedItem>
  <relatedItem type="reviews" n="1">
      <bibl>
         <ptr target="http://papyri.info/biblio/19700"/>
         <!--ignore - start, i.e. SoSOL users may not edit this-->
         <title level="m" type="main">The Architecture of Alexandria and Egypt c. 300 BC to AD 700. (Yale University Press Pelican History of Art.)</title>
         <author>McKENZIE, Judith</author>
         <!--ignore - stop-->
      </bibl>
  </relatedItem>
  <idno type="pi">82972</idno>
  <seg type="original" subtype="cr" resp="#BP">Georg A. Plattner, RA 2009, pp. 111-113.</seg>
</bibl>
