<?xml version="1.0" encoding="UTF-8"?>
<bibl xmlns="http://www.tei-c.org/ns/1.0"
      xml:id="b84554"
      type="book"
      subtype="authored"
      xml:lang="fr">
   <title level="m" type="main">Un édifice royal inachevé du quartier royal à Alexandrie. Étude suivie de: Hélène Fragaki &amp; Anne-Marie Guimier-Sorbets, Un fragment de corniche peinte hellénistique à Alexandrie</title>
   <series>
      <title level="s" type="main">Études Alexandrines</title>
      <biblScope type="volume">31</biblScope>
   </series>
   <author>
      <forename>Hélène</forename>
      <surname>Fragaki</surname>
   </author>
   <author>
      <forename>Anne-Marie</forename>
      <surname>Guimier-Sorbets</surname>
   </author>
   <date>2013</date>
   <pubPlace>Alexandrie</pubPlace>
   <publisher>Centre d'Études Alexandrines (Diffusion: de Boccard, Paris)</publisher>
   <note type="pageCount">149</note>
   <note type="illustration">tabl., 131 figg. n./bl. et coul.</note>
   <note resp="#BP">H.Fr., Un édifice royal inachevé du quartier royal à Alexandrie, pp. 9-126, tabl., 120 figg. n./bl. et coul.: Introduction; - Catalogue des blocs; - Chronologie [fin du IIIe s. av. J.-C.]; - Identification des vestiges [complexe monumental public, vraisemblablement annexé au théâtre]; - Pratique et théorie de la construction; - Conclusion. - H.Fr. &amp; A.-M. G.-S., Un fragment de corniche peinte hellénistique à Alexandrie [bloc en calcaire découvert en 1996 lors des fouilles d'urgence conduites par le CEAlex dans le jardin de l'ancien Consulat britannique], pp. 127-148, 11 figg. n./bl. et coul.: Description; - Comparaisons; - Particularités stylistiques et techniques; - Conclusion.</note>
   <idno type="pi">84554</idno>
   <idno type="bp">2013-0430</idno>
   <idno type="isbn">978-2-11-129851-4</idno>
   <seg type="original" subtype="index" resp="#BP">241 Alexandrie 810 840</seg>
   <seg type="original" subtype="titre" resp="#BP">Hélène Fragaki, Un édifice royal inachevé du quartier royal à Alexandrie. Étude suivie de: Hélène Fragaki &amp; Anne-Marie Guimier-Sorbets, Un fragment de corniche peinte hellénistique à Alexandrie = Études Alexandrines. 31.</seg>
   <seg type="original" subtype="publication" resp="#BP">Alexandrie, Centre d'Études Alexandrines (Diffusion: de Boccard, Paris), 2013, 4°, 149 pp., tabl., 131 figg. n./bl. et coul. ISBN 978-2-11-129851-4. €40.</seg>
   <seg type="original" subtype="resume" resp="#BP">H.Fr., Un édifice royal inachevé du quartier royal à Alexandrie, pp. 9-126, tabl., 120 figg. n./bl. et coul.: Introduction; - Catalogue des blocs; - Chronologie [fin du IIIe s. av. J.-C.]; - Identification des vestiges [complexe monumental public, vraisemblablement annexé au théâtre]; - Pratique et théorie de la construction; - Conclusion. - H.Fr. &amp; A.-M. G.-S., Un fragment de corniche peinte hellénistique à Alexandrie [bloc en calcaire découvert en 1996 lors des fouilles d'urgence conduites par le CEAlex dans le jardin de l'ancien Consulat britannique], pp. 127-148, 11 figg. n./bl. et coul.: Description; - Comparaisons; - Particularités stylistiques et techniques; - Conclusion.</seg>
   <seg type="original" subtype="cr" resp="#BP">C.R. par Paul Edmund Stanwick, BMCRev &lt; http://bmcr.brynmawr.edu/2014/2014-08-20.html &gt;. - Jacques des Courtils, REA 116 (2014) pp. 394-395. - Pierre Gros, RA 2015, pp. 219-222. - Yoshifumi Yasuoka, BibO 72 (2015) coll. 454-457.</seg>
   <seg type="original" subtype="nom" resp="#BP">Fragaki Guimier-Sorbets</seg>
</bibl>
