<bibl xml:id="b11953" type="book">
  <title level="m" type="main">Columbia Papyri VIII. (American Studies in Papyrology. 28.)</title>
  <author n="1">
    <surname>BAGNALL</surname>
    <forename>Roger S.</forename>
  </author>
  <author n="2">
    <forename>Timothy T.</forename>
    <surname>RENNER</surname>
  </author>
  <author n="3">
    <forename>Klaas A.</forename>
    <surname>WORP</surname>
  </author>
  <pubPlace>Atlanta, Georgia</pubPlace>
  <publisher>Scholars Press</publisher>
  <date>1990</date>
  <note type="pageCount">238</note>
  <note type="illustration">dont 2 dépl.</note>
  <note resp="#BP">P. Col. VIII, 192-246: Literary texts (192-207); -Documentary texts (208-246).</note>
  <idno type="bp">90/0036</idno>
  <idno type="bp_old">96/3/016, 97/1/010</idno>
  <note type="titre" resp="#BPLegacy">BAGNALL Roger S., Timothy T. RENNER and Klaas A. WORP, Columbia Papyri VIII. (American Studies in Papyrology. 28.)</note>
  <note type="publication" resp="#BPLegacy">Atlanta, Georgia, Scholars Press, 1990, 8°, 238 pp. et 57 pll., dont 2 dépl.</note>
  <note type="index" resp="#BPLegacy">141.4</note>
  <note type="indexBis" resp="#BPLegacy">141.4 P. Col. VIII</note>
  <note type="nom" resp="#BPLegacy">Bagnall Renner Worp</note>
</bibl>