<bibl xmlns="http://www.tei-c.org/ns/1.0" xml:id="b28617" type="review">
  <author>Hans Jucker</author>
  <date>1984</date>
  <biblScope type="pp">pp. 542-547</biblScope>
  <biblScope type="issue">56</biblScope>
  <relatedItem type="appearsIn">
    <bibl>
      <ptr target="bibl:1315"/>
      <!--ignore - start, i.e. SoSOL users may not edit this-->
      <title level="j" type="short">Gnomon</title>
      <!--ignore - stop-->
    </bibl>
  </relatedItem>
  <relatedItem type="reviews" n="1">
    <bibl>
      <ptr target="bibl:9385"/>
      <!--ignore - start, i.e. SoSOL users may not edit this-->
      <title level="m" type="main">Repertorio d'arte dell'Egitto greco-romano. Serie B [Pittura]. Volume III: Klaus Parlasca, Ritratti di mummie. [Tavole 121-158. Numeri 497-674.]</title>
      <author>Adriani, Achille</author>
      <!--ignore - stop-->
    </bibl>
  </relatedItem>
  <seg type="original" subtype="cr" resp="#BP">Hans Jucker, Gnomon 56 (1984) pp. 542-547.</seg>
</bibl>