<?xml version="1.0" encoding="UTF-8"?>
<bibl xmlns="http://www.tei-c.org/ns/1.0"
      xml:id="b77121"
      type="article"
      subtype="journal">
   <title level="a" type="main">Untersuchungen zu den ägyptischen Nomenprägungen X. 20. unterägyptischer Gau und die Stadt Pelusion. Zusammenfassung der Ergebnisse von Nomenprägungen (I)-X.</title>
   <author n="1">
      <forename>Angelo</forename>
      <surname>Geissen</surname>
   </author>
   <author n="2">
      <forename>Manfred</forename>
      <surname>Weber</surname>
   </author>
   <date>2008</date>
   <biblScope type="pp" from="277" to="305">277-305</biblScope>
   <note resp="#BP">Suite de: ZPE 160 (2007) pp. 275-300, 6 figg., 3 pll. - 20. unterägyptischer Gau: Arabia: a. Die Kulte; - b. Die Münzen; - c. Ergebnis. - Die Stadt Pelusion: a. Die Kulte; - b. Die Münzen; - c. Ergebnis. - Zusammenfassung der Ergebnisse von Nomenprägungen (I)-X: I. Liste der Aufsätze Nomenprägungen (I)-X; - II. Zum Begriff Gaue und Gau-Münzen; - III. Die "Gaugötter"; - IV. Zur Ikonographie; - Tabelle 1: Gaue und Städte mit den zugehörigen Legenden; - Tabelle 2: Die auf den Münzen belegten Gaue nach der kanonischen Zählung; - Tabelle 3: Kennzeichen der ägyptischen Gottheiten auf den Münzen.</note>
   <ptr target="http://www.jstor.org/stable/20476461"/>
   <relatedItem type="appearsIn">
      <bibl>
         <ptr target="http://papyri.info/biblio/511"/>
         <!--ignore - start, i.e. SoSOL users may not edit this-->
         <title level="j" type="short-BP">ZPE</title>
         <!--ignore - stop-->
      </bibl>
   </relatedItem>
   <biblScope type="issue">164</biblScope>
   <idno type="pi">77121</idno>
   <idno type="bp">2008-0277</idno>
   <idno type="bp_old">08/3/113</idno>
   <seg type="original" subtype="index" resp="#BP">712 920</seg>
   <seg type="original" subtype="titre" resp="#BP">GEISSEN Angelo und Manfred WEBER, Untersuchungen zu den ägyptischen Nomenprägungen X. 20. unterägyptischer Gau und die Stadt Pelusion. Zusammenfassung der Ergebnisse von Nomenprägungen (I)-X.</seg>
   <seg type="original" subtype="publication" resp="#BP">ZPE 164 (2008) pp. 277-305, 3 tabl., 5 figg., 1pl.</seg>
   <seg type="original" subtype="resume" resp="#BP">Suite de: ZPE 160 (2007) pp. 275-300, 6 figg., 3 pll. - 20. unterägyptischer Gau: Arabia: a. Die Kulte; - b. Die Münzen; - c. Ergebnis. - Die Stadt Pelusion: a. Die Kulte; - b. Die Münzen; - c. Ergebnis. - Zusammenfassung der Ergebnisse von Nomenprägungen (I)-X: I. Liste der Aufsätze Nomenprägungen (I)-X; - II. Zum Begriff Gaue und Gau-Münzen; - III. Die "Gaugötter"; - IV. Zur Ikonographie; - Tabelle 1: Gaue und Städte mit den zugehörigen Legenden; - Tabelle 2: Die auf den Münzen belegten Gaue nach der kanonischen Zählung; - Tabelle 3: Kennzeichen der ägyptischen Gottheiten auf den Münzen.</seg>
   <seg type="original" subtype="nom" resp="#BP">Geissen Weber</seg>
</bibl>
