<?xml version="1.0" encoding="UTF-8"?>
<bibl xmlns="http://www.tei-c.org/ns/1.0" xml:id="b97441" type="review">
  <author>
    <forename>Bruno</forename>
    <surname>Centrone</surname>
  </author>
  <date>2000</date>
  <biblScope type="pp" from="338" to="342">338-342</biblScope>
  <relatedItem type="appearsIn">
    <bibl>
      <ptr target="https://papyri.info/biblio/419" />
      <!--ignore - start, i.e. SoSOL users may not edit this-->
      <!--ignore - stop-->
    </bibl>
  </relatedItem>
  <biblScope type="issue">128</biblScope>
  <relatedItem type="reviews" n="1">
    <bibl>
      <ptr target="https://papyri.info/biblio/68414" />
      <!--ignore - start, i.e. SoSOL users may not edit this-->
      <!--ignore - stop-->
    </bibl>
  </relatedItem>
  <idno type="pi">97441</idno>
  <seg type="original" subtype="cr" resp="#BP">Bruno Centrone, RivFil 128 (2000 [2002]) pp. 338-342.</seg>
</bibl>