<?xml version="1.0" encoding="UTF-8"?><bibl xmlns="http://www.tei-c.org/ns/1.0" xml:id="b12724" type="book">
  <title level="m" type="main">Corpus dei Papiri filosofici greci e latini (CPF). Testi e lessico nei papiri di cultura greca e latina. Parte I: Autori noti. Vol. 1**. (Unione Accademica Nazionale. Accademia Toscana di Scienze e Lettere "La Colombaria".)</title>
  <pubPlace>Firenze</pubPlace>
  <publisher>L.S. Olschki</publisher>
  <date>1992</date>
  <note type="pageCount">497</note>
  <note type="prefacePageCount">xliv</note>
  <note resp="#BP">Filosofi (D-M).</note>
  <idno type="pi">12724</idno>
  <idno type="bp">92/0195</idno>
  <idno type="bp_old">96/1/045, 97/4/027</idno>
  <idno type="isbn">88-222-3918-0</idno>
  <seg type="original" subtype="titre" resp="#BP">Corpus dei Papiri filosofici greci e latini (CPF). Testi e lessico nei papiri di cultura greca e latina. Parte I: Autori noti. Vol. 1**. (Unione Accademica Nazionale. Accademia Toscana di Scienze e Lettere "La Colombaria".)</seg>
  <seg type="original" subtype="publication" resp="#BP">Firenze, L.S. Olschki, 1992, 8°, xliv-497 pp. ISBN 88-222-3918-0. L. 245.000.</seg>
  <seg type="original" subtype="index" resp="#BP">141.4 / 141.5 364 / 365 Philosophica</seg>
  <seg type="original" subtype="indexBis" resp="#BP">141.4 / 141.5 C.P.F. I, 1**</seg>
</bibl>