<?xml version="1.0" encoding="UTF-8"?>
<bibl xmlns="http://www.tei-c.org/ns/1.0"
      xml:id="b50580"
      type="article"
      subtype="journal">
   <title level="a" type="main">Frammenti tolemaici.</title>
   <author n="1">
      <forename>Sergio</forename>
      <surname>Daris</surname>
   </author>
   <date>1975</date>
   <biblScope type="pp" from="188" to="191">188-191</biblScope>
   <note resp="#BP">P. Med. Inv. 68.88. Dichiarazione all'archiphylakites del villaggio di Arsinoe. Sec. II/I a.C. - 2. Inv. 172. Frammento di lettera. 27 gennaio 82 a.C. - 3. Inv. 69.50 recto. Frammento di corrispondenza ufficiale. Sec. III/II a.C.</note>
   <relatedItem type="appearsIn">
      <bibl>
         <ptr target="http://papyri.info/biblio/174"/>
         <!--ignore - start, i.e. SoSOL users may not edit this-->
         <title level="j" type="short-BP">ChrEg</title>
         <!--ignore - stop-->
      </bibl>
   </relatedItem>
   <biblScope type="issue">50</biblScope>
   <relatedItem type="mentions" n="1">
      <bibl>
         <idno type="invNo">P. Med. Inv. 172</idno>
      </bibl>
   </relatedItem>
   <relatedItem type="mentions" n="2">
      <bibl>
         <idno type="invNo">P. Med. Inv. 68.88</idno>
      </bibl>
   </relatedItem>
   <relatedItem type="mentions" n="3">
      <bibl>
         <idno type="invNo">P. Med. Inv. 69.50 recto</idno>
      </bibl>
   </relatedItem>
   <relatedItem type="mentions" n="4">
      <bibl>
         <title level="s" type="short">SB</title>
         <biblScope type="vol">XIV</biblScope>
         <biblScope type="num">11860</biblScope>
         <idno type="ddb">sb;14;11860</idno>
      </bibl>
   </relatedItem>
   <relatedItem type="mentions" n="5">
      <bibl>
         <title level="s" type="short">SB</title>
         <biblScope type="vol">XIV</biblScope>
         <biblScope type="num">11861</biblScope>
         <idno type="ddb">sb;14;11861</idno>
      </bibl>
   </relatedItem>
   <relatedItem type="mentions" n="6">
      <bibl>
         <title level="s" type="short">SB</title>
         <biblScope type="vol">XIV</biblScope>
         <biblScope type="num">11862</biblScope>
         <idno type="ddb">sb;14;11862</idno>
      </bibl>
   </relatedItem>
   <idno type="pi">50580</idno>
   <idno type="bp">1975-0140</idno>
   <seg type="original" subtype="index" resp="#BP">141.4 364 Epistulae</seg>
   <seg type="original" subtype="indexBis" resp="#BP">141.4 P. Med. Inv. 172; 68.88; 69.50 recto</seg>
   <seg type="original" subtype="titre" resp="#BP">Daris Sergio, Frammenti tolemaici.</seg>
   <seg type="original" subtype="publication" resp="#BP">ChrEg 50 (1975) Nos 99-100, pp. 188-191.</seg>
   <seg type="original" subtype="resume" resp="#BP">P. Med. Inv. 68.88. Dichiarazione all'archiphylakites del villaggio di Arsinoe. Sec. II/I a.C. - 2. Inv. 172. Frammento di lettera. 27 gennaio 82 a.C. - 3. Inv. 69.50 recto. Frammento di corrispondenza ufficiale. Sec. III/II a.C.</seg>
   <seg type="original" subtype="sbSeg" resp="#BP">S.B. XIV, 11860-11862.</seg>
   <seg type="original" subtype="nom" resp="#BP">Daris</seg>
</bibl>
