<?xml version="1.0" encoding="UTF-8"?>
<bibl xmlns="http://www.tei-c.org/ns/1.0"
      xml:id="b69980"
      type="article"
      subtype="journal">
   <title level="a" type="main">Magisches Glöckchen.</title>
   <author n="1">
      <forename>Ellen</forename>
      <surname>Doetsch-Amberger</surname>
   </author>
   <date>2001</date>
   <biblScope type="pp" from="43" to="50">43-50</biblScope>
   <note resp="#BP">Collection privée. Clochette de bronze (H. 3,5 cm) en forme de protomè d'Apis. Des divinités égyptiennes sont représentées sur la paroi: bélier, uraeus, faucon, etc. Égypte, fin de l'époque ptolémaïque ou époque romaine. Observations sur les usages profanes, religieux et magiques des cloches et des clochettes.</note>
   <relatedItem type="appearsIn">
      <bibl>
         <ptr target="http://papyri.info/biblio/1319"/>
         <!--ignore - start, i.e. SoSOL users may not edit this-->
         <title level="j" type="short-BP">Göttinger Miszellen</title>
         <!--ignore - stop-->
      </bibl>
   </relatedItem>
   <biblScope type="issue">180</biblScope>
   <idno type="pi">69980</idno>
   <idno type="bp">2001-0257</idno>
   <idno type="bp_old">01/2/048</idno>
   <seg type="original" subtype="index" resp="#BP">713 880</seg>
   <seg type="original" subtype="titre" resp="#BP">DOETSCH-AMBERGER Ellen, Magisches Glöckchen.</seg>
   <seg type="original" subtype="publication" resp="#BP">Göttinger Miszellen 180 (2001) pp. 43-50, 4 figg.</seg>
   <seg type="original" subtype="resume" resp="#BP">Collection privée. Clochette de bronze (H. 3,5 cm) en forme de protomè d'Apis. Des divinités égyptiennes sont représentées sur la paroi: bélier, uraeus, faucon, etc. Égypte, fin de l'époque ptolémaïque ou époque romaine. Observations sur les usages profanes, religieux et magiques des cloches et des clochettes.</seg>
   <seg type="original" subtype="nom" resp="#BP">Doetsch-Amberger</seg>
</bibl>
