<?xml version="1.0" encoding="UTF-8"?>
<bibl xmlns="http://www.tei-c.org/ns/1.0" xml:id="b15867" type="book">
   <title level="m" type="main">Alexandrie.</title>
   <series>
      <title level="s" type="main">Trois-Continents. Poche-Couleur.</title>
      <biblScope type="volume">44</biblScope>
   </series>
   <date>2000</date>
   <pubPlace>Monaco</pubPlace>
   <publisher>Éditions du Rocher</publisher>
   <note type="pageCount">144</note>
   <note type="illustration">nombr. ill. coul.</note>
   <note resp="#BP">Alexandre le Grand. - Les Alexandrie. - Alexandrie: La ville ancienne; - La ville moderne; - Les vestiges du passé.</note>
   <idno type="pi">15867</idno>
   <idno type="bp">2000-0007</idno>
   <idno type="bp_old">00/2/001</idno>
   <idno type="isbn">2-268-03503-4 / 282-640193-4</idno>
   <seg type="original" subtype="index" resp="#BP">241 Alexandrie</seg>
   <seg type="original" subtype="titre" resp="#BP">Alexandrie. (Trois-Continents. Poche-Couleur. 44.)</seg>
   <seg type="original" subtype="publication" resp="#BP">Monaco, Éditions du Rocher, 2000, 8°, 144 pp., nombr. ill. coul. ISBN 2-268-03503-4 / 282-640193-4.</seg>
   <seg type="original" subtype="resume" resp="#BP">Alexandre le Grand. - Les Alexandrie. - Alexandrie: La ville ancienne; - La ville moderne; - Les vestiges du passé.</seg>
</bibl>