<?xml version="1.0" encoding="UTF-8"?>
<bibl xmlns="http://www.tei-c.org/ns/1.0" xml:id="b15897" type="book">
   <title level="m" type="main">Bibliotheca Bodmeriana. La collection des Papyrus Bodmer. Manuscrits de textes grecs classiques, grecs et coptes bibliques et de littérature chrétienne, du 2e au 9e siècle.</title>
   <series>
      <title level="s" type="main">P. Bodmer</title>
   </series>
   <author n="1">
      <forename>Martin</forename>
      <surname>Bircher</surname>
   </author>
   <date>2000</date>
   <pubPlace>München</pubPlace>
   <publisher>K.G. Saur</publisher>
   <note type="pageCount">4872</note>
   <note type="prefacePageCount">cxl</note>
   <note resp="#BP">Reproduction intégrale: 1. Graeca classica [P. Bodmer I, IV, XXV, XXVI]; - 2-4. Graeca biblica et christiana [P. Bodmer II, V, VII, VIII, IX, X, XI, XII; - XIII, XIV, XV; - XVII, XX, XXIV]; - 5. Graeca christiana [P. Bodmer XXIX, XXX-XXXVII, XXXVIII]; - 6-7. Coptica biblica [P. Bodmer XVI, XVIII, XIX, XXI; - XXII, XXIII]; - 8-10. Planches. - 1, pp. ix-xii: Martin BIRCHER, Avant-propos. Traduction par Rodolphe KASSER; - xiii-xv: Vorwort; - xvii-xix: Foreword. Translation by Colin AUSTIN. - 1, pp. xxi-xxxvii: Rodolphe KASSER, Introduction [sur la genèse de la collection]; - xxxix-lii: Einführung. Übersetzung von Martin BIRCHER; - liii-lix: Introduction. Translation by Colin AUSTIN.</note>
   <idno type="pi">15897</idno>
   <idno type="bp">2000-0070</idno>
   <idno type="bp_old">00/2/012, 06/2/024</idno>
   <idno type="isbn">3-598-22551-2 (voll</idno>
   <seg type="original" subtype="index" resp="#BP">141.13 / 141.4</seg>
   <seg type="original" subtype="indexBis" resp="#BP">141.13 / 141.4 P. Bodmer</seg>
   <seg type="original" subtype="titre" resp="#BP">BIRCHER Martin (édité par la Fondation Martin Bodmer par les soins de), Bibliotheca Bodmeriana. La collection des Papyrus Bodmer. Manuscrits de textes grecs classiques, grecs et coptes bibliques et de littérature chrétienne, du 2e au 9e siècle. </seg>
   <seg type="original" subtype="publication" resp="#BP">München, K.G. Saur, 2000, 8°, cxl-4872 pp. ISBN 3-598-22551-2 (voll. 1-10); - 3-598-22552-0 (voll. 1-7); - 3-598-22553-9 (voll. 8-10). DM 2600 (voll. 1-10); - 1820 (voll. 1-7); - 780 (voll. 8-10).</seg>
   <seg type="original" subtype="resume" resp="#BP">Reproduction intégrale: 1. Graeca classica [P. Bodmer I, IV, XXV, XXVI]; - 2-4. Graeca biblica et christiana [P. Bodmer II, V, VII, VIII, IX, X, XI, XII; - XIII, XIV, XV; - XVII, XX, XXIV]; - 5. Graeca christiana [P. Bodmer XXIX, XXX-XXXVII, XXXVIII]; - 6-7. Coptica biblica [P. Bodmer XVI, XVIII, XIX, XXI; - XXII, XXIII]; - 8-10. Planches. - 1, pp. ix-xii: Martin BIRCHER, Avant-propos. Traduction par Rodolphe KASSER; - xiii-xv: Vorwort; - xvii-xix: Foreword. Translation by Colin AUSTIN. - 1, pp. xxi-xxxvii: Rodolphe KASSER, Introduction [sur la genèse de la collection]; - xxxix-lii: Einführung. Übersetzung von Martin BIRCHER; - liii-lix: Introduction. Translation by Colin AUSTIN.</seg>
   <seg type="original" subtype="cr" resp="#BP">C.R. par Colin Austin, CR N.S., 51 (2001) pp. 185-186.</seg>
   <seg type="original" subtype="nom" resp="#BP">Bircher Kasser Austin</seg>
</bibl>
