<bibl xml:id="b32271" type="review">
  <author>Dominik Maschek</author>
  <date>2009</date>
  <biblScope type="pp">pp. 249-251</biblScope>
  <biblScope type="issue">24</biblScope>
  <relatedItem type="appearsIn">
    <bibl>
      <ptr target="bibl:1949"/>
      <!--ignore - start, i.e. SoSOL users may not edit this-->
      <title level="j" type="short">Tyche</title>
      <!--ignore - stop-->
    </bibl>
  </relatedItem>
  <relatedItem type="reviews" n="1">
    <bibl>
      <ptr target="bibl:21785"/>
      <!--ignore - start, i.e. SoSOL users may not edit this-->
      <title level="m" type="main">Survey and Excavation. Mons Claudianus 1987-1993. Volume III: Ceramic Vessels and Related Objects, by Roberta TOMBER, Kathryn KNOWLES, Donald BAILEY and Ross THOMAS, with a contribution by Hélène CUVIGNY.</title>
      <author>MAXFIELD, Valerie A.</author>
      <!--ignore - stop-->
    </bibl>
  </relatedItem>
  <note type="cr" resp="#BPLegacy">C.R. par Dominik Maschek, Tyche 24 (2009) pp. 249-251.</note>
</bibl>