<?xml version="1.0" encoding="UTF-8"?>
<bibl xmlns="http://www.tei-c.org/ns/1.0"
      xml:id="b49755"
      type="article"
      subtype="journal">
   <title level="a" type="main">Urkunden aus Panopolis. III.</title>
   <series>
      <title level="s" type="main">P. Köln Panop</title>
   </series>
   <author n="1">
      <forename>Louise C.</forename>
      <surname>Youtie</surname>
   </author>
   <author n="2">
      <forename>Dieter</forename>
      <surname>Hagedorn</surname>
   </author>
   <author n="3">
      <forename>Herbert C.</forename>
      <surname>Youtie</surname>
   </author>
   <date>1973</date>
   <biblScope type="pp" from="101" to="170">101-170</biblScope>
   <note resp="#BP">P. Köln Panop. 20-31.</note>
   <relatedItem type="appearsIn">
      <bibl>
         <ptr target="http://papyri.info/biblio/511"/>
         <!--ignore - start, i.e. SoSOL users may not edit this-->
         <title level="j" type="short-BP">ZPE</title>
         <!--ignore - stop-->
      </bibl>
   </relatedItem>
   <biblScope type="issue">10</biblScope>
   <relatedItem type="mentions" n="1">
      <bibl>
         <title level="s" type="short">SB</title>
         <biblScope type="vol">XII</biblScope>
         <biblScope type="num">11213</biblScope>
         <idno type="ddb">sb;12;11213</idno>
      </bibl>
   </relatedItem>
   <relatedItem type="mentions" n="2">
      <bibl>
         <title level="s" type="short">SB</title>
         <biblScope type="vol">XII</biblScope>
         <biblScope type="num">11214</biblScope>
         <idno type="ddb">sb;12;11214</idno>
      </bibl>
   </relatedItem>
   <relatedItem type="mentions" n="3">
      <bibl>
         <title level="s" type="short">SB</title>
         <biblScope type="vol">XII</biblScope>
         <biblScope type="num">11215</biblScope>
         <idno type="ddb">sb;12;11215</idno>
      </bibl>
   </relatedItem>
   <relatedItem type="mentions" n="4">
      <bibl>
         <title level="s" type="short">SB</title>
         <biblScope type="vol">XII</biblScope>
         <biblScope type="num">11216</biblScope>
         <idno type="ddb">sb;12;11216</idno>
      </bibl>
   </relatedItem>
   <relatedItem type="mentions" n="5">
      <bibl>
         <title level="s" type="short">SB</title>
         <biblScope type="vol">XII</biblScope>
         <biblScope type="num">11217</biblScope>
         <idno type="ddb">sb;12;11217</idno>
      </bibl>
   </relatedItem>
   <relatedItem type="mentions" n="6">
      <bibl>
         <title level="s" type="short">SB</title>
         <biblScope type="vol">XII</biblScope>
         <biblScope type="num">11218</biblScope>
         <idno type="ddb">sb;12;11218</idno>
      </bibl>
   </relatedItem>
   <relatedItem type="mentions" n="7">
      <bibl>
         <title level="s" type="short">SB</title>
         <biblScope type="vol">XII</biblScope>
         <biblScope type="num">11219</biblScope>
         <idno type="ddb">sb;12;11219</idno>
      </bibl>
   </relatedItem>
   <relatedItem type="mentions" n="8">
      <bibl>
         <title level="s" type="short">SB</title>
         <biblScope type="vol">XII</biblScope>
         <biblScope type="num">11220</biblScope>
         <idno type="ddb">sb;12;11220</idno>
      </bibl>
   </relatedItem>
   <relatedItem type="mentions" n="9">
      <bibl>
         <title level="s" type="short">SB</title>
         <biblScope type="vol">XII</biblScope>
         <biblScope type="num">11221</biblScope>
         <idno type="ddb">sb;12;11221</idno>
      </bibl>
   </relatedItem>
   <relatedItem type="mentions" n="10">
      <bibl>
         <title level="s" type="short">SB</title>
         <biblScope type="vol">XII</biblScope>
         <biblScope type="num">11222</biblScope>
         <idno type="ddb">sb;12;11222</idno>
      </bibl>
   </relatedItem>
   <relatedItem type="mentions" n="11">
      <bibl>
         <title level="s" type="short">SB</title>
         <biblScope type="vol">XII</biblScope>
         <biblScope type="num">11223</biblScope>
         <idno type="ddb">sb;12;11223</idno>
      </bibl>
   </relatedItem>
   <relatedItem type="mentions" n="12">
      <bibl>
         <title level="s" type="short">SB</title>
         <biblScope type="vol">XII</biblScope>
         <biblScope type="num">11224</biblScope>
         <idno type="ddb">sb;12;11224</idno>
      </bibl>
   </relatedItem>
   <idno type="pi">49755</idno>
   <idno type="bp">1973-0554</idno>
   <seg type="original" subtype="index" resp="#BP">141.4</seg>
   <seg type="original" subtype="indexBis" resp="#BP">141.4 P. Köln Panop.</seg>
   <seg type="original" subtype="titre" resp="#BP">Youtie Louise C., Dieter Hagedorn und Herbert C. Youtie, Urkunden aus Panopolis. III.</seg>
   <seg type="original" subtype="publication" resp="#BP">ZPE 10 (1973) pp. 101-170 et pll. III-V.</seg>
   <seg type="original" subtype="resume" resp="#BP">P. Köln Panop. 20-31.</seg>
   <seg type="original" subtype="sbSeg" resp="#BP">S.B. XII, 11213-11224.</seg>
   <seg type="original" subtype="cr" resp="#BP">C.R. par Jean Bingen, ChrEg 48 (1973) No. 95, pp. 185-189 (concerne aussi P. Köln Panop. I-II).</seg>
   <seg type="original" subtype="nom" resp="#BP">Youtie Hagedorn</seg>
</bibl>
